enmerkar/__init__.py
enmerkar/extract.py
enmerkar/middleware.py
enmerkar/management/__init__.py
enmerkar/management/commands/__init__.py
enmerkar/management/commands/babel.py
enmerkar/templatetags/__init__.py
enmerkar/templatetags/babel.py
enmerkar-0.7.1.dist-info/AUTHORS
enmerkar-0.7.1.dist-info/COPYING
enmerkar-0.7.1.dist-info/METADATA
enmerkar-0.7.1.dist-info/WHEEL
enmerkar-0.7.1.dist-info/entry_points.txt
enmerkar-0.7.1.dist-info/top_level.txt
enmerkar-0.7.1.dist-info/RECORD
